odoo/addons/payment_environment/README.rst
odoo/addons/payment_environment/__init__.py
odoo/addons/payment_environment/__manifest__.py
odoo/addons/payment_environment/i18n/payment_environment.pot
odoo/addons/payment_environment/models/__init__.py
odoo/addons/payment_environment/models/payment_acquirer.py
odoo/addons/payment_environment/readme/CONFIGURE.rst
odoo/addons/payment_environment/readme/CONTRIBUTORS.rst
odoo/addons/payment_environment/readme/DESCRIPTION.rst
odoo/addons/payment_environment/readme/INSTALL.rst
odoo/addons/payment_environment/readme/ROADMAP.rst
odoo/addons/payment_environment/readme/USAGE.rst
odoo/addons/payment_environment/static/description/icon.png
odoo/addons/payment_environment/static/description/index.html
odoo/addons/payment_environment/views/payment_acquirer.xml
odoo13_addon_payment_environment-13.0.1.1.0.dist-info/METADATA
odoo13_addon_payment_environment-13.0.1.1.0.dist-info/WHEEL
odoo13_addon_payment_environment-13.0.1.1.0.dist-info/top_level.txt
odoo13_addon_payment_environment-13.0.1.1.0.dist-info/RECORD
